ckssocli/__init__.py
ckssocli/ck_configuration.py
ckssocli/ck_help.py
ckssocli/ck_login.py
ckssocli/ck_sso_cli.py
ckssocli/version.py
ck_sso_cli-2.0.3.dist-info/LICENSE
ck_sso_cli-2.0.3.dist-info/METADATA
ck_sso_cli-2.0.3.dist-info/WHEEL
ck_sso_cli-2.0.3.dist-info/entry_points.txt
ck_sso_cli-2.0.3.dist-info/top_level.txt
ck_sso_cli-2.0.3.dist-info/RECORD
